supervisor_react/__init__.py
supervisor_react/__main__.py
supervisor_react/statics/asset-manifest.json
supervisor_react/statics/icon.png
supervisor_react/statics/index.html
supervisor_react/statics/manifest.json
supervisor_react/statics/robots.txt
supervisor_react/statics/static/js/main.5a2f7e99.js
supervisor_react/statics/static/js/main.5a2f7e99.js.LICENSE.txt
supervisor_react-0.7.0.dist-info/LICENCE
supervisor_react-0.7.0.dist-info/METADATA
supervisor_react-0.7.0.dist-info/WHEEL
supervisor_react-0.7.0.dist-info/entry_points.txt
supervisor_react-0.7.0.dist-info/RECORD
