Metadata-Version: 2.1
Name: supervisor-react
Version: 0.7.0
Summary: A web interface for supervisor
Home-page: https://github.com/jouve/supervisor-react
License: GPL-3.0-only
Author: Cyril Jouve
Author-email: jv.cyril@gmail.com
Requires-Python: >=3.11,<4.0
Classifier: License :: OSI Approved :: GNU General Public License v3 (GPLv3)
Classifier: Programming Language :: Python :: 3
Classifier: Programming Language :: Python :: 3.11
Classifier: Programming Language :: Python :: 3.12
Classifier: Programming Language :: Python :: 3.13
Requires-Dist: aiofiles
Requires-Dist: httpx
Requires-Dist: starlette
Requires-Dist: uvicorn
Project-URL: Repository, https://github.com/jouve/supervisor-react
